setup.cfg
setup.py
src/_correlatemodule.c
src/_lineshapemodule.c
stsci/__init__.py
stsci.convolve.egg-info/PKG-INFO
stsci.convolve.egg-info/SOURCES.txt
stsci.convolve.egg-info/dependency_links.txt
stsci.convolve.egg-info/namespace_packages.txt
stsci.convolve.egg-info/not-zip-safe
stsci.convolve.egg-info/requires.txt
stsci.convolve.egg-info/top_level.txt
stsci/convolve/__init__.py
stsci/convolve/convolve.py
stsci/convolve/iraf_frame.py
stsci/convolve/lineshape.py
stsci/convolve/version.py
stsci/convolve/tests/__init__.py
stsci/convolve/tests/test_convolve.py
stsci/convolve/tests/test_irafframe.py