Metadata-Version: 1.1
Name: stsci.convolve
Version: 2.2.1
Summary: Image array convolution functions
Home-page: http://www.stsci.edu/resources/software_hardware/stsci_python
Author: Todd Miller
Author-email: help@stsci.edu
License: UNKNOWN
Platform: UNKNOWN
Classifier: Intended Audience :: Science/Research
Classifier: License :: OSI Approved :: BSD License
Classifier: Operating System :: OS Independent
Classifier: Programming Language :: Python
Classifier: Topic :: Scientific/Engineering :: Astronomy
Classifier: Topic :: Scientific/Engineering :: Mathematics
Classifier: Topic :: Software Development :: Libraries :: Python Modules
